[
    {
        "name": "Pneu MICHELIN PRIMACY 4 205/55 R16 91 V", 
        "price": 75.9, 
        "url": "https://www.norauto.fr/p/pneu-michelin-primacy-4-205-55-r16-91-v-2173602.html"
    }, 
    {
        "name": "Pneu GOODYEAR EFFICIENTGRIP PERFORMANCE 2 205/55 R16 91 V", 
        "price": 64.9, 
        "url": "https://www.norauto.fr/p/pneu-goodyear-efficientgrip-performance-2-205-55-r16-91-v-2210470.html"
    }, 
    {
        "name": "Pneu NORAUTO PREVENSYS 3 205/55 R16 91 V", 
        "price": 58.9, 
        "url": "https://www.norauto.fr/p/pneu-norauto-prevensys-3-205-55-r16-91-v-20833.html"
    }, 
    {
        "name": "Pneu RUNWAY ENDURO HP 205/55 R16 91 V", 
        "price": 35.9, 
        "url": "https://www.norauto.fr/p/pneu-runway-enduro-hp-205-55-r16-91-v-2152802.html"
    }, 
    {
        "name": "Pneu BLACK-STAR ST-01 205/55 R16 91 V", 
        "price": 40.9, 
        "url": "https://www.norauto.fr/p/pneu-black-star-reconditionne-st-01-205-55-r16-91-v-2271346.html"
    }, 
    {
        "name": "Pneu GOODYEAR EFFICIENTGRIP PERFORMANCE 2 205/55 R16 91 W", 
        "price": 65.9, 
        "url": "https://www.norauto.fr/p/pneu-goodyear-efficientgrip-performance-2-205-55-r16-91-w-2210407.html"
    }, 
    {
        "name": "Pneu HANKOOK VENTUS PRIME 3 K125 XL 205/55 R16 94 W XL", 
        "price": 62.5, 
        "url": "https://www.norauto.fr/p/pneu-hankook-ventus-prime-3-k125-205-55-r16-94-w-xl-2057206.html"
    }, 
    {
        "name": "Pneu MICHELIN PRIMACY 4 205/55 R16 91 H", 
        "price": 72.5, 
        "url": "https://www.norauto.fr/p/pneu-michelin-primacy-4-205-55-r16-91-h-2179573.html"
    }, 
    {
        "name": "Pneu HEADWAY HH301 205/55 R16 91 V", 
        "price": 35.9, 
        "url": "https://www.norauto.fr/p/pneu-headway-hh301-205-55-r16-91-v-2000195.html"
    }, 
    {
        "name": "Pneu CONTINENTAL ECOCONTACT 6 205/55 R16 91 V", 
        "price": 69.9, 
        "url": "https://www.norauto.fr/p/pneu-continental-ecocontact-6-205-55-r16-91-v-64710.html"
    }, 
    {
        "name": "Pneu BRIDGESTONE TURANZA T005 205/55 R16 91 V", 
        "price": 64.9, 
        "url": "https://www.norauto.fr/p/pneu-bridgestone-turanza-t005-205-55-r16-91-v-2102540.html"
    }, 
    {
        "name": "Pneu BRIDGESTONE TURANZA T005 205/55 R16 91 W", 
        "price": 66.5, 
        "url": "https://www.norauto.fr/p/pneu-bridgestone-turanza-t005-205-55-r16-91-w-2177012.html"
    }, 
    {
        "name": "Pneu UNIROYAL RAINSPORT 5 205/55 R16 91 V", 
        "price": 60.9, 
        "url": "https://www.norauto.fr/p/pneu-uniroyal-rainsport-5-205-55-r16-91-v-2199629.html"
    }, 
    {
        "name": "Pneu HANKOOK VENTUS PRIME 3 K125 205/55 R16 91 V", 
        "price": 60.5, 
        "url": "https://www.norauto.fr/p/pneu-hankook-ventus-prime-3-k125-205-55-r16-91-v-2055330.html"
    }, 
    {
        "name": "Pneu GOODYEAR EFFICIENTGRIP Runflat 205/55 R16 91 V Runflat", 
        "price": 81.9, 
        "url": "https://www.norauto.fr/p/pneu-goodyear-efficientgrip-205-55-r16-91-v-moextended-runflat-425856.html"
    }, 
    {
        "name": "Pneu MICHELIN PRIMACY 4 205/55 R16 91 W", 
        "price": 81.5, 
        "url": "https://www.norauto.fr/p/pneu-michelin-primacy-4-205-55-r16-91-w-2173604.html"
    }, 
    {
        "name": "Pneu MICHELIN PRIMACY 4 XL 205/55 R16 94 V XL", 
        "price": 90.5, 
        "url": "https://www.norauto.fr/p/pneu-michelin-primacy-4-205-55-r16-94-v-xl-2173603.html"
    }, 
    {
        "name": "Pneu GOODYEAR EFFICIENTGRIP PERFORMANCE 205/55 R16 91 V", 
        "price": 61.5, 
        "url": "https://www.norauto.fr/p/pneu-goodyear-efficientgrip-performance-205-55-r16-91-v-657015.html"
    }, 
    {
        "name": "Pneu MICHELIN ENERGY SAVER 205/55 R16 91 W", 
        "price": 89.9, 
        "url": "https://www.norauto.fr/p/pneu-michelin-energy-saver-205-55-r16-91-w--318209.html"
    }, 
    {
        "name": "Pneu HANKOOK VENTUS PRIME 2 K115 205/55 R16 91 W", 
        "price": 66.5, 
        "url": "https://www.norauto.fr/p/pneu-hankook-ventus-prime-2-k115-205-55-r16-91-w--465893.html"
    }, 
    {
        "name": "Pneu MICHELIN PRIMACY 3 Runflat 205/55 R16 91 V Runflat", 
        "price": 95.5, 
        "url": "https://www.norauto.fr/p/pneu-michelin-primacy-3-205-55-r16-91-v-runflat-783791.html"
    }, 
    {
        "name": "Pneu GOODYEAR EFFICIENTGRIP Runflat 205/55 R16 91 W Runflat", 
        "price": 84.5, 
        "url": "https://www.norauto.fr/p/pneu-goodyear-efficientgrip-205-55-r16-91-w-runflat-466839.html"
    }, 
    {
        "name": "Pneu HANKOOK VENTUS PRIME 3 K125 205/55 R16 91 H", 
        "price": 58.5, 
        "url": "https://www.norauto.fr/p/pneu-hankook-ventus-prime-3-k125-205-55-r16-91-h-2057219.html"
    }, 
    {
        "name": "Pneu CONTINENTAL ECOCONTACT 6 205/55 R16 91 W", 
        "price": 76.5, 
        "url": "https://www.norauto.fr/p/pneu-continental-ecocontact-6-205-55-r16-91-w-66645.html"
    }, 
    {
        "name": "Pneu CONTINENTAL CONTIECOCONTACT 5 205/55 R16 91 V", 
        "price": 71.5, 
        "url": "https://www.norauto.fr/p/pneu-continental-contiecocontact-5-205-55-r16-91-v-mo-379399.html"
    }, 
    {
        "name": "Pneu CONTINENTAL CONTIPREMIUMCONTACT 5 205/55 R16 91 H", 
        "price": 68.9, 
        "url": "https://www.norauto.fr/p/pneu-continental-contipremiumcontact-5-205-55-r16-91-h-26268.html"
    }, 
    {
        "name": "Pneu FIRESTONE ROADHAWK 205/55 R16 91 H", 
        "price": 55.9, 
        "url": "https://www.norauto.fr/p/pneu-firestone-roadhawk-205-55-r16-91-h-2097558.html"
    }, 
    {
        "name": "Pneu CONTINENTAL CONTIECOCONTACT 5 205/55 R16 91 V", 
        "price": 71.5, 
        "url": "https://www.norauto.fr/p/pneu-continental-contiecocontact-5-205-55-r16-91-v-ao-928420.html"
    }, 
    {
        "name": "Pneu CONTINENTAL CONTIECOCONTACT 5 205/55 R16 91 H", 
        "price": 71.9, 
        "url": "https://www.norauto.fr/p/pneu-continental-contiecocontact-5-205-55-r16-91-h-mo-407194.html"
    }, 
    {
        "name": "Pneu RUNWAY ENDURO HP XL 205/55 R16 94 W XL", 
        "price": 42.9, 
        "url": "https://www.norauto.fr/p/pneu-runway-enduro-hp-205-55-r16-94-w-xl-2137669.html"
    }, 
    {
        "name": "Pneu CONTINENTAL ECOCONTACT 6 XL 205/55 R16 94 V XL", 
        "price": 81.5, 
        "url": "https://www.norauto.fr/p/pneu-continental-ecocontact-6-205-55-r16-94-v-xl-fiat-92837.html"
    }, 
    {
        "name": "Pneu UNIROYAL RAINSPORT 5 XL 205/55 R16 94 V XL", 
        "price": 65.5, 
        "url": "https://www.norauto.fr/p/pneu-uniroyal-rainsport-5-205-55-r16-94-v-xl-2199632.html"
    }, 
    {
        "name": "Pneu DUNLOP SPORT BLURESPONSE 205/55 R16 91 V", 
        "price": 61.9, 
        "url": "https://www.norauto.fr/p/pneu-dunlop-sport-bluresponse-205-55-r16-91-v-657013.html"
    }, 
    {
        "name": "Pneu FIRESTONE ROADHAWK 205/55 R16 91 V", 
        "price": 55.9, 
        "url": "https://www.norauto.fr/p/pneu-firestone-roadhawk-205-55-r16-91-v-2102555.html"
    }, 
    {
        "name": "Pneu DUNLOP SPORT BLURESPONSE 205/55 R16 91 W", 
        "price": 65.5, 
        "url": "https://www.norauto.fr/p/pneu-dunlop-sport-bluresponse-205-55-r16-91-w-657019.html"
    }, 
    {
        "name": "Pneu PIRELLI CINTURATO P7 BLUE 205/55 R16 91 V", 
        "price": 65.5, 
        "url": "https://www.norauto.fr/p/pneu-pirelli-cinturato-p7-blue-205-55-r16-91-v-2115566.html"
    }, 
    {
        "name": "Pneu NORAUTO PREVENSYS 3 205/55 R16 91 H", 
        "price": 60.5, 
        "url": "https://www.norauto.fr/p/pneu-norauto-prevensys-3-205-55-r16-91-h-20832.html"
    }, 
    {
        "name": "Pneu DUNLOP SPORT BLURESPONSE 205/55 R16 91 H", 
        "price": 61.9, 
        "url": "https://www.norauto.fr/p/pneu-dunlop-sport-bluresponse-205-55-r16-91-h-657009.html"
    }, 
    {
        "name": "Pneu MICHELIN PRIMACY 3 205/55 R16 91 V", 
        "price": 66.5, 
        "url": "https://www.norauto.fr/p/pneu-michelin-primacy-3-205-55-r16-91-v-467156.html"
    }, 
    {
        "name": "Pneu CONTINENTAL CONTIECOCONTACT 5 205/55 R16 91 V", 
        "price": 69.9, 
        "url": "https://www.norauto.fr/p/pneu-continental-contiecocontact-5-205-55-r16-91-v-470954.html"
    }, 
    {
        "name": "Pneu FALKEN ZIEX ZE310 ECORUN 205/55 R16 91 V", 
        "price": 55.5, 
        "url": "https://www.norauto.fr/p/pneu-falken-ziex-ze310-ecorun-205-55-r16-91-v-69718.html"
    }, 
    {
        "name": "Pneu MICHELIN PILOT SPORT 4 205/55 R16 91 W", 
        "price": 88.5, 
        "url": "https://www.norauto.fr/p/pneu-michelin-pilot-sport-4-205-55-r16-91-w-2146318.html"
    }, 
    {
        "name": "Pneu PIRELLI CINTURATO P7 205/55 R16 91 V", 
        "price": 62.5, 
        "url": "https://www.norauto.fr/p/pneu-pirelli-cinturato-p7-205-55-r16-91-v--970576.html"
    }, 
    {
        "name": "Pneu GOODYEAR EFFICIENTGRIP PERFORMANCE XL 205/55 R16 94 V XL", 
        "price": 79.9, 
        "url": "https://www.norauto.fr/p/pneu-goodyear-efficientgrip-performance-205-55-r16-94-v-xl-2115802.html"
    }, 
    {
        "name": "Pneu NEXEN N BLUE HD PLUS 205/55 R16 91 V", 
        "price": 48.9, 
        "url": "https://www.norauto.fr/p/pneu-nexen-n-blue-hd-plus-205-55-r16-91-v-2155043.html"
    }, 
    {
        "name": "Pneu BRIDGESTONE TURANZA T005 205/55 R16 91 H", 
        "price": 69.9, 
        "url": "https://www.norauto.fr/p/pneu-bridgestone-turanza-t005-205-55-r16-91-h-2102543.html"
    }, 
    {
        "name": "Pneu PIRELLI CINTURATO P7 205/55 R16 91 W", 
        "price": 79.9, 
        "url": "https://www.norauto.fr/p/pneu-pirelli-cinturato-p7-205-55-r16-91-w-ao-769141.html"
    }, 
    {
        "name": "Pneu DUNLOP SPORT BLURESPONSE 205/55 R16 91 V", 
        "price": 61.9, 
        "url": "https://www.norauto.fr/p/pneu-dunlop-sport-bluresponse-205-55-r16-91-v-vw-lrr-684887.html"
    }
]